LICENSE
MANIFEST.in
README.rst
setup.py
base/__init__.py
base/admin.py
base/apps.py
base/models.py
base/tests.py
base/views.py
base/static/.DS_Store
base/static/_assets/.DS_Store
base/static/_assets/css/custom.min.css
base/static/_assets/css/signin.css
base/static/_assets/img/logo-dark.png
base/static/_assets/img/logo-nav.svg
base/static/_assets/img/logo.png
base/static/_assets/img/refs/code-crunchers.png
base/static/_assets/img/refs/csssecrets.png
base/static/_assets/img/refs/divjoy-custom.png
base/static/_assets/img/refs/divjoy-joy.png
base/static/_assets/img/refs/divjoy-light.png
base/static/_assets/img/refs/eloquentjavascript.png
base/static/_assets/img/refs/flexbox-froggy-pro.png
base/static/_assets/img/refs/grid-garden.png
base/static/_assets/img/refs/htmlandcss.png
base/static/_assets/img/refs/themes.3rdwavemedia.com_coderpro_bs4_-700.png
base/static/_assets/img/refs/themes.3rdwavemedia.com_devcard_bs4_2.0_-700.png
base/static/_assets/img/refs/themes.3rdwavemedia.com_nova-pro_bs4_-700.png
base/static/_assets/js/bsa.js
base/static/_assets/js/custom.js
base/static/_assets/scss/custom.scss
base/static/_vendors/.DS_Store
base/static/_vendors/Bootswatch/.DS_Store
base/static/_vendors/Bootswatch/CNAME
base/static/_vendors/Bootswatch/favicon.ico
base/static/_vendors/Bootswatch/index.html
base/static/_vendors/Bootswatch/api/2.json
base/static/_vendors/Bootswatch/api/3.json
base/static/_vendors/Bootswatch/api/4.json
base/static/_vendors/Bootswatch/cerulean/_bootswatch.scss
base/static/_vendors/Bootswatch/cerulean/_variables.scss
base/static/_vendors/Bootswatch/cerulean/bootstrap.css
base/static/_vendors/Bootswatch/cerulean/bootstrap.min.css
base/static/_vendors/Bootswatch/cerulean/index.html
base/static/_vendors/Bootswatch/cerulean/thumbnail.png
base/static/_vendors/Bootswatch/cosmo/_bootswatch.scss
base/static/_vendors/Bootswatch/cosmo/_variables.scss
base/static/_vendors/Bootswatch/cosmo/bootstrap.css
base/static/_vendors/Bootswatch/cosmo/bootstrap.min.css
me_django_base.egg-info/PKG-INFO
me_django_base.egg-info/SOURCES.txt
me_django_base.egg-info/dependency_links.txt
me_django_base.egg-info/top_level.txt